deployutils/__init__.py
deployutils/configs.py
deployutils/copy.py
deployutils/crypt.py
deployutils/djd.py
deployutils/filesys.py
deployutils/helpers.py
deployutils/s3.py
deployutils/apps/__init__.py
deployutils/apps/django_deployutils/__init__.py
deployutils/apps/django_deployutils/authentication.py
deployutils/apps/django_deployutils/compat.py
deployutils/apps/django_deployutils/logging.py
deployutils/apps/django_deployutils/middleware.py
deployutils/apps/django_deployutils/redirects.py
deployutils/apps/django_deployutils/settings.py
deployutils/apps/django_deployutils/themes.py
deployutils/apps/django_deployutils/thread_local.py
deployutils/apps/django_deployutils/urlbuilders.py
deployutils/apps/django_deployutils/backends/__init__.py
deployutils/apps/django_deployutils/backends/auth.py
deployutils/apps/django_deployutils/backends/encrypted_cookies.py
deployutils/apps/django_deployutils/backends/jwt_session_store.py
deployutils/apps/django_deployutils/backends/session_base.py
deployutils/apps/django_deployutils/management/__init__.py
deployutils/apps/django_deployutils/management/commands/__init__.py
deployutils/apps/django_deployutils/management/commands/base.py
deployutils/apps/django_deployutils/management/commands/cryptic_media.py
deployutils/apps/django_deployutils/management/commands/decrypt_session.py
deployutils/apps/django_deployutils/management/commands/download_configs.py
deployutils/apps/django_deployutils/management/commands/download_resources.py
deployutils/apps/django_deployutils/management/commands/encrypt_session.py
deployutils/apps/django_deployutils/management/commands/generate_webpack_paths.py
deployutils/apps/django_deployutils/management/commands/loadfixtures.py
deployutils/apps/django_deployutils/management/commands/package_theme.py
deployutils/apps/django_deployutils/management/commands/referenced_assets.py
deployutils/apps/django_deployutils/management/commands/referenced_extends.py
djaodjin_deployutils-0.14.2.dist-info/licenses/LICENSE.txt
djaodjin_deployutils-0.14.2.dist-info/METADATA
djaodjin_deployutils-0.14.2.dist-info/WHEEL
djaodjin_deployutils-0.14.2.dist-info/entry_points.txt
djaodjin_deployutils-0.14.2.dist-info/top_level.txt
djaodjin_deployutils-0.14.2.dist-info/RECORD
