Metadata-Version: 2.4
Name: djaodjin-deployutils
Version: 0.14.2
Summary: Deploy webapps hosted on djaodjin.com
Author-email: The DjaoDjin Team <help@djaodjin.com>
Maintainer-email: The DjaoDjin Team <help@djaodjin.com>
License: BSD-2-Clause
Project-URL: repository, https://github.com/djaodjin/djaodjin-deployutils
Project-URL: documentation, https://djaodjin-deployutils.readthedocs.io/
Project-URL: changelog, https://github.com/djaodjin/djaodjin-deployutils/changelog
Keywords: deployutils,session,django,flask
Classifier: Framework :: Django
Classifier: Framework :: Flask
Classifier: Environment :: Web Environment
Classifier: Programming Language :: Python
Classifier: License :: OSI Approved :: BSD License
Requires-Python: >=3.7
License-File: LICENSE.txt
Requires-Dist: boto3>=1.12.31
Requires-Dist: cryptography>=2.2.2
Requires-Dist: pip>=8.1.2
Requires-Dist: PyJWT>=1.6.1
Requires-Dist: python-dateutil>=2.4.2
Requires-Dist: pytz>=2021.1
Requires-Dist: six>=1.10.0
Requires-Dist: requests>=2.22.0
Provides-Extra: django
Requires-Dist: Django>=3.2; python_version < "3.9" and extra == "django"
Requires-Dist: Django>=4.2; (python_version >= "3.9" and python_version < "3.12") and extra == "django"
Requires-Dist: Django>=5.1; python_version >= "3.12" and extra == "django"
Requires-Dist: djangorestframework>=3.14.0; python_version < "3.9" and extra == "django"
Requires-Dist: djangorestframework>=3.15.2; python_version >= "3.9" and extra == "django"
Requires-Dist: jinja2>=2.8.1; extra == "django"
Requires-Dist: monotonic>=1.1; extra == "django"
Provides-Extra: flask
Requires-Dist: Flask>=0.11; extra == "flask"
Dynamic: license-file
